pyw/__init__.py
pyw_core-0.0.0.post3.dist-info/METADATA
pyw_core-0.0.0.post3.dist-info/WHEEL
pyw_core-0.0.0.post3.dist-info/licenses/LICENSE
pyw_core-0.0.0.post3.dist-info/RECORD
