Metadata-Version: 2.4
Name: pyw-core
Version: 0.0.0.post3
Summary: Reserved placeholder for pyw-core (umbrella namespace)
Project-URL: Homepage, https://github.com/pythonWoods/pyw-core
Project-URL: Documentation, https://pythonwoods.dev/docs/pyw-core/latest/
Project-URL: Issues, https://github.com/pythonWoods/pyw-core/issues
Project-URL: Changelog, https://github.com/pythonWoods/pyw-core/releases
Author: pythonWoods
License: MIT
License-File: LICENSE
Classifier: Development Status :: 2 - Pre-Alpha
Classifier: License :: OSI Approved :: MIT License
Classifier: Programming Language :: Python :: 3 :: Only
Classifier: Programming Language :: Python :: 3.11
Classifier: Typing :: Typed
Requires-Python: >=3.9
